its_utils/__init__.py
its_utils/debug_prompt.py
its_utils/string_math.py
its_utils/word_math.py
ItsUtils-0.2.2.dist-info/LICENSE
ItsUtils-0.2.2.dist-info/METADATA
ItsUtils-0.2.2.dist-info/WHEEL
ItsUtils-0.2.2.dist-info/top_level.txt
ItsUtils-0.2.2.dist-info/RECORD
