Metadata-Version: 2.1
Name: ItsUtils
Version: 0.2.2
Summary: A Package containing utils created by ItsNameless
Author: ItsNameless
License: MIT License
Project-URL: Homepage, https://github.com/TheItsProjects/ItsUtils
Project-URL: Repository, https://github.com/TheItsProjects/ItsUtils
Project-URL: Issue Tracker, https://github.com/TheItsProjects/ItsUtils/issues
Classifier: Programming Language :: Python :: 3
Classifier: License :: OSI Approved :: MIT License
Classifier: Operating System :: OS Independent
Requires-Python: >=3.8
License-File: LICENSE
